odoo/addons/sm_crm_donation/__init__.py
odoo/addons/sm_crm_donation/__manifest__.py
odoo/addons/sm_crm_donation/data/crm_stage_data.xml
odoo/addons/sm_crm_donation/data/crm_team_data.xml
odoo/addons/sm_crm_donation/data/utm_source_data.xml
odoo/addons/sm_crm_donation/models/__init__.py
odoo/addons/sm_crm_donation/views/crm_lead_views.xml
odoo12_addon_sm_crm_donation-12.0.0.0.2.dist-info/METADATA
odoo12_addon_sm_crm_donation-12.0.0.0.2.dist-info/WHEEL
odoo12_addon_sm_crm_donation-12.0.0.0.2.dist-info/top_level.txt
odoo12_addon_sm_crm_donation-12.0.0.0.2.dist-info/RECORD
